record_type-2023.1.post1.dist-info/METADATA
record_type-2023.1.post1.dist-info/WHEEL
record_type-2023.1.post1.dist-info/licenses/LICENSE
records.py
record_type-2023.1.post1.dist-info/RECORD
