Metadata-Version: 2.1
Name: record-type
Version: 2023.1.post1
Summary: A record type for Python
Author-Email: Brett Cannon <brett@python.org>
License: BSD 3-Clause License
Classifier: Development Status :: 3 - Alpha
Project-URL: Repository, https://github.com/brettcannon/record-type
Requires-Python: >=3.11
Provides-Extra: test
Provides-Extra: benchmark
Requires-Dist: pytest; extra == "test"
Requires-Dist: richbench; extra == "benchmark"
